tabularbench/__init__.py
tabularbench/attacks/__init__.py
tabularbench/attacks/caa/caa.py
tabularbench/attacks/capgd/capgd.py
tabularbench/attacks/cpgd/cpgd.py
tabularbench/attacks/moeva/__init__.py
tabularbench/attacks/moeva/adversarial_problem.py
tabularbench/attacks/moeva/history_callback.py
tabularbench/attacks/moeva/moeva.py
tabularbench/attacks/moeva/operators.py
tabularbench/attacks/objective_calculator.py
tabularbench/attacks/utils.py
tabularbench/benchmark/benchmark.py
tabularbench/benchmark/model_utils.py
tabularbench/benchmark/subset_utils.py
tabularbench/constraints/__init__.py
tabularbench/constraints/backend.py
tabularbench/constraints/constraints.py
tabularbench/constraints/constraints_backend_executor.py
tabularbench/constraints/constraints_checker.py
tabularbench/constraints/constraints_executor.py
tabularbench/constraints/constraints_fixer.py
tabularbench/constraints/constraints_parser.py
tabularbench/constraints/numpy_backend.py
tabularbench/constraints/pytorch_backend.py
tabularbench/constraints/relation_constraint.py
tabularbench/constraints/utils.py
tabularbench/dataloaders/__init__.py
tabularbench/dataloaders/adversarial/__init__.py
tabularbench/dataloaders/adversarial/madry.py
tabularbench/dataloaders/aliases.py
tabularbench/dataloaders/dataloader.py
tabularbench/dataloaders/default.py
tabularbench/dataloaders/fast_dataloader.py
tabularbench/dataloaders/generative/ctgan.py
tabularbench/dataloaders/generative/gan_file.py
tabularbench/dataloaders/generative/goggle.py
tabularbench/dataloaders/generative/tablegan.py
tabularbench/dataloaders/generative/tvae.py
tabularbench/dataloaders/generative/wgan.py
tabularbench/dataloaders/mix/cutmix.py
tabularbench/datasets/aliases.py
tabularbench/datasets/dataset.py
tabularbench/datasets/dataset_factory.py
tabularbench/datasets/processing.py
tabularbench/datasets/samples/__init__.py
tabularbench/datasets/samples/ctu_13_neris.py
tabularbench/datasets/samples/lcld.py
tabularbench/datasets/samples/malware.py
tabularbench-0.1.0.dist-info/LICENSE
tabularbench-0.1.0.dist-info/METADATA
tabularbench-0.1.0.dist-info/WHEEL
tabularbench-0.1.0.dist-info/RECORD
