Metadata-Version: 2.1
Name: tabularbench
Version: 0.1.0
Summary: TabularBench: Adversarial robustness benchmark for tabular data
Author: Thibault Simonetto
Author-email: thibault.simonetto@uni.lu
Requires-Python: >=3.8.1,<3.11
Classifier: Programming Language :: Python :: 3
Classifier: Programming Language :: Python :: 3.9
Classifier: Programming Language :: Python :: 3.10
Requires-Dist: einops (>=0.6.1,<0.7.0)
Requires-Dist: h5py (>=3.11.0,<4.0.0)
Requires-Dist: lifelines (>=0.27.8,<0.28.0)
Requires-Dist: numpy (<1.24)
Requires-Dist: optuna (==3.1.1)
Requires-Dist: pandas (>=1.4.1,<2.0.0)
Requires-Dist: pyarrow (>=16.1.0,<17.0.0)
Requires-Dist: pymoo (==0.5.0)
Requires-Dist: pytorch-tabnet (>=4.1.0,<5.0.0)
Requires-Dist: requests (>=2.25.1,<3.0.0)
Requires-Dist: scikit-learn (>=1.0.2,<2.0.0)
Requires-Dist: tables (==3.7.0)
Requires-Dist: torch (==1.12.1)
Requires-Dist: torchattacks (==3.4.0)
